ws/__init__.py
ws/client.py
ws/commands/__init__.py
ws/commands/completion.py
ws/commands/echo_server.py
ws/commands/listen.py
ws/commands/ping.py
ws/commands/pong.py
ws/commands/session.py
ws/commands/tail.py
ws/commands/text_byte.py
ws/console.py
ws/main.py
ws/options.py
ws/parameters.py
ws/settings.py
ws/utils/__init__.py
ws/utils/command.py
ws/utils/decorators.py
ws/utils/documentation.py
ws/utils/io.py
ws/utils/lexer.py
ws/utils/size.py
websockets_cli-0.3.0.dist-info/LICENSE
websockets_cli-0.3.0.dist-info/METADATA
websockets_cli-0.3.0.dist-info/WHEEL
websockets_cli-0.3.0.dist-info/entry_points.txt
websockets_cli-0.3.0.dist-info/RECORD
