Metadata-Version: 2.1
Name: websockets-cli
Version: 0.3.0
Summary: A simple yet powerful websocket cli
Home-page: https://pyws.readthedocs.io
License: Apache-2.0
Keywords: websocket,cli,trio,anyio
Author: le_woudar
Author-email: lewoudar@gmail.com
Requires-Python: >=3.8,<4.0
Classifier: Environment :: Web Environment
Classifier: Framework :: Trio
Classifier: Intended Audience :: Developers
Classifier: License :: OSI Approved :: Apache Software License
Classifier: Operating System :: OS Independent
Classifier: Programming Language :: Python :: 3
Classifier: Programming Language :: Python :: 3.8
Classifier: Programming Language :: Python :: 3.9
Classifier: Programming Language :: Python :: 3.10
Classifier: Programming Language :: Python :: 3.11
Classifier: Programming Language :: Python :: Implementation :: PyPy
Classifier: Topic :: Terminals
Requires-Dist: certifi (>=2023.11.17,<2024.0.0)
Requires-Dist: click (>=8.1.7,<9.0.0)
Requires-Dist: click-didyoumean (>=0.3.0,<0.4.0)
Requires-Dist: prompt-toolkit (>=3.0.41,<4.0.0)
Requires-Dist: pydantic (>=2.5.2,<3.0.0)
Requires-Dist: pydantic-settings (>=2.1.0,<3.0.0)
Requires-Dist: rich (>=13.7.0,<14.0.0)
Requires-Dist: shellingham (>=1.5.0,<2.0.0)
Requires-Dist: tomli (>=2.0.1,<3.0.0)
Requires-Dist: trio-websocket (>=0.11.1,<0.12.0)
Project-URL: Bug Tracker, https://github.com/lewoudar/ws/issues
Project-URL: Changelog, https://github.com/lewoudar/ws/blob/main/CHANGELOG.md
Project-URL: Documentation, https://pyws.readthedocs.io
Project-URL: Repository, https://github.com/lewoudar/ws
